Metadata-Version: 1.1
Name: zc.generationalset
Version: 0.4.0
Summary: *****************
Home-page: https://bitbucket.org/zc/generationalset
Author: Jim Fulton
Author-email: jim@zope.com
License: ZPL 2.1
Keywords: real-time UI,ZODB
Platform: UNKNOWN
Classifier: Development Status :: 5 - Production/Stable
Classifier: Intended Audience :: Developers
Classifier: License :: OSI Approved :: MIT License
Classifier: Programming Language :: Python
Classifier: Programming Language :: Python :: 2
Classifier: Programming Language :: Python :: 2.7
Classifier: Programming Language :: Python :: 3
Classifier: Programming Language :: Python :: 3.4
Classifier: Programming Language :: Python :: 3.5
Classifier: Programming Language :: Python :: 3.6
